{"id":1682,"problem_id":2,"submitted_at":"2022-09-02T17:58:29.332894Z","status":"SUCCEEDED","cost":12661,"error":"","file_url":"https://minivinci-submissions.s3.amazonaws.com/user60_problem_2_21113c64-6e03-4563-9812-cdd9f5c609aa.isl?X-Amz-Algorithm=AWS4-HMAC-SHA256\u0026X-Amz-Credential=AKIA35VZNBCZRCI77IEN%2F20220903%2Fus-east-1%2Fs3%2Faws4_request\u0026X-Amz-Date=20220903T061147Z\u0026X-Amz-Expires=900\u0026X-Amz-SignedHeaders=host\u0026X-Amz-Signature=ee81091b7423fea2049f04b7ec8d8e66cb09e26b11f5eda8563dee52bf1c225b"}
