{"id":28254,"problem_id":23,"submitted_at":"2022-09-04T05:12:18.215831Z","status":"SUCCEEDED","cost":20556,"error":"","file_url":"https://minivinci-submissions.s3.amazonaws.com/user60_problem_23_50501805-71ce-4970-9052-2537af1bd2d0.isl?X-Amz-Algorithm=AWS4-HMAC-SHA256\u0026X-Amz-Credential=AKIA35VZNBCZRCI77IEN%2F20220904%2Fus-east-1%2Fs3%2Faws4_request\u0026X-Amz-Date=20220904T055702Z\u0026X-Amz-Expires=900\u0026X-Amz-SignedHeaders=host\u0026X-Amz-Signature=3d184cc9aa09e1b175d86c1d53819c15dd80f467fe1e2c957d5af1812d92ea70"}
