{"id":35848,"problem_id":5,"submitted_at":"2022-09-04T14:16:52.817705Z","status":"SUCCEEDED","cost":11334,"error":"","file_url":"https://minivinci-submissions.s3.amazonaws.com/user60_problem_5_a9191cd7-c5c7-4a91-869f-22014ec13d05.isl?X-Amz-Algorithm=AWS4-HMAC-SHA256\u0026X-Amz-Credential=AKIA35VZNBCZRCI77IEN%2F20220904%2Fus-east-1%2Fs3%2Faws4_request\u0026X-Amz-Date=20220904T150622Z\u0026X-Amz-Expires=900\u0026X-Amz-SignedHeaders=host\u0026X-Amz-Signature=3c1916a9b0de5f9a7f6d2fb3c338c1a7b6b17684598ad76f2f4a84aa51613d18"}
