{"id":38029,"problem_id":23,"submitted_at":"2022-09-04T17:01:57.010001Z","status":"SUCCEEDED","cost":18481,"error":"","file_url":"https://minivinci-submissions.s3.amazonaws.com/user60_problem_23_f6a3c4ca-1d17-4a3e-9bbb-14317b60a078.isl?X-Amz-Algorithm=AWS4-HMAC-SHA256\u0026X-Amz-Credential=AKIA35VZNBCZRCI77IEN%2F20220904%2Fus-east-1%2Fs3%2Faws4_request\u0026X-Amz-Date=20220904T173202Z\u0026X-Amz-Expires=900\u0026X-Amz-SignedHeaders=host\u0026X-Amz-Signature=46215a24f355921a3d99806079c634b6edd837915ee9c7044046beed33937661"}
