{"id":6409,"problem_id":23,"submitted_at":"2022-09-03T00:59:58.851909Z","status":"SUCCEEDED","score":21194,"file_url":"https://minivinci-submissions.s3.amazonaws.com/user60_problem_23_71a8920e-b833-458d-adcc-c5e724e7b11a.isl?X-Amz-Algorithm=AWS4-HMAC-SHA256\u0026X-Amz-Credential=AKIA35VZNBCZRCI77IEN%2F20220903%2Fus-east-1%2Fs3%2Faws4_request\u0026X-Amz-Date=20220903T033639Z\u0026X-Amz-Expires=900\u0026X-Amz-SignedHeaders=host\u0026X-Amz-Signature=687b59c40ebd085bfc09bbc9af002a00092f70304124cda6c0d5de134f5a44fb"}
